src/__init__.py
src/scratch.py
py2scratch-0.0.2.dist-info/METADATA
py2scratch-0.0.2.dist-info/WHEEL
py2scratch-0.0.2.dist-info/licenses/LICENSE
py2scratch-0.0.2.dist-info/RECORD
