Metadata-Version: 2.3
Name: py2scratch
Version: 0.0.2
Summary: A module that converts Python to Scratch (.sb3) files.
Project-URL: Homepage, https://github.com/Crunchitect/py2scratch
Author-email: Crunchitect <crunchitect@gmail.com>
License-File: LICENSE
Classifier: License :: OSI Approved :: MIT License
Classifier: Operating System :: OS Independent
Classifier: Programming Language :: Python :: 3
Requires-Python: >=3.9
